LICENSE
MANIFEST.in
README.md
requirements.txt
setup.py
w1kp/__init__.py
w1kp/_version.py
w1kp/utils.py
w1kp.egg-info/PKG-INFO
w1kp.egg-info/SOURCES.txt
w1kp.egg-info/dependency_links.txt
w1kp.egg-info/entry_points.txt
w1kp.egg-info/requires.txt
w1kp.egg-info/top_level.txt
w1kp/data/__init__.py
w1kp/data/dataset.py
w1kp/data/experiment.py
w1kp/data/mturk.py
w1kp/model/__init__.py
w1kp/model/distance.py
w1kp/model/feature_extractor.py
w1kp/model/image_generator.py
w1kp/run/__init__.py
w1kp/run/dreamsim_server.py
w1kp/run/generate_2afc_hit_images.py
w1kp/run/generate_images.py
w1kp/run/generate_magnitude_hit_images.py
w1kp/run/measure_variability.py
w1kp/run/sdxl_server.py
w1kp/run/split_dataset.py
w1kp/run/trainer.py
w1kp/run/upload_2afc_hit_images.py
w1kp/run/upload_magnitude_hit_images.py
w1kp/run/verify_2afc_hit_batch.py
w1kp/run/verify_magnitude_hit_batch.py