Metadata-Version: 2.1
Name: w1kp
Version: 0.0.1
Summary: Words worth a thousand pictures
Home-page: https://github.com/castorini/w1kp
Author: Raphael Tang
Author-email: r33tang@uwaterloo.ca
License: MIT
Platform: UNKNOWN
Requires-Python: >=3.10
License-File: LICENSE
